coding_devops_sdk/__init__.py
coding_devops_sdk/config.py
coding_devops_sdk/settings.toml
coding_devops_sdk/ci/__init__.py
coding_devops_sdk/ci/plugins.py
coding_devops_sdk/depot/__init__.py
coding_devops_sdk/depot/git.py
coding_devops_sdk/openapi/__init__.py
coding_devops_sdk/openapi/auth.py
coding_devops_sdk/openapi/client.py
coding_devops_sdk/openapi/depot.py
coding_devops_sdk/openapi/exceptions.py
coding_devops_sdk/openapi/models.py
coding_devops_sdk/openapi/project.py
coding_devops_sdk/openapi/team.py
coding_devops_sdk/service_hook/__init__.py
coding_devops_sdk/service_hook/models.py
coding_devops_sdk_py-0.1.2.dist-info/LICENSE
coding_devops_sdk_py-0.1.2.dist-info/METADATA
coding_devops_sdk_py-0.1.2.dist-info/WHEEL
coding_devops_sdk_py-0.1.2.dist-info/top_level.txt
coding_devops_sdk_py-0.1.2.dist-info/RECORD
