Metadata-Version: 2.1
Name: coding-devops-sdk-py
Version: 0.1.2
Summary: Python SDK for Coding DevOps
Author-email: "QuantTide Inc." <opensource@quanttide.com>
License: Apache License
Classifier: Programming Language :: Python :: 3
Requires-Python: >=3
License-File: LICENSE
Requires-Dist: gitpython
Requires-Dist: dynaconf
